Metadata-Version: 2.1
Name: pymirror-rmugicag
Version: 0.0.11
Summary: Text comparator UI
Home-page: https://github.com/rmugicag/pymirror
Author: Ricardo Mugica
Author-email: rmugicag@gmail.com
Project-URL: Bug Tracker, https://github.com/rmugicag/pymirror/issues
Classifier: Programming Language :: Python :: 3
Classifier: License :: OSI Approved :: MIT License
Classifier: Operating System :: OS Independent
Requires-Python: >=3.6
License-File: LICENSE
